pytangle/__init__.py
pytangle/api.py
pytangle/connectivity.py
pytangle/endpoints.py
pytangle/utils.py
pytangle-0.0.2.dist-info/LICENSE
pytangle-0.0.2.dist-info/METADATA
pytangle-0.0.2.dist-info/WHEEL
pytangle-0.0.2.dist-info/top_level.txt
pytangle-0.0.2.dist-info/RECORD
