Metadata-Version: 2.1
Name: pytangle
Version: 0.0.2
Summary: A python wrapper for crowdtangle API endpoints
Home-page: https://github.com/hide-ous/pytangle/
Author: Mattia Samory
Author-email: mattia.samory@gmail.com
License: UNKNOWN
Download-URL: https://github.com/hide-ous/pytangle/archive/v0.0.1.tar.gz
Keywords: crowdtangle,api,wrapper
Platform: UNKNOWN
Classifier: Programming Language :: Python :: 3
Classifier: License :: OSI Approved :: GNU General Public License v3 (GPLv3)
Classifier: Operating System :: OS Independent
Requires-Python: >=3.5
Requires-Dist: requests (>=2.9.1)
Requires-Dist: ratelimit (>=2.2.1)
Requires-Dist: python-dateutil (>=2.8.1)
